botai_manager/__init__.py
botai_manager/admin.py
botai_manager/apps.py
botai_manager/models.py
botai_manager/tests.py
botai_manager/urls.py
botai_manager/views.py
botai_manager/__pycache__/__init__.cpython-38.pyc
botai_manager/__pycache__/models.cpython-38.pyc
botai_manager/migrations/__init__.py
django_botai_manager-1.2.dist-info/LICENSE
django_botai_manager-1.2.dist-info/METADATA
django_botai_manager-1.2.dist-info/WHEEL
django_botai_manager-1.2.dist-info/top_level.txt
django_botai_manager-1.2.dist-info/RECORD
