Metadata-Version: 2.1
Name: django-botai-manager
Version: 1.2
Summary: A Django app to conduct web-based botai web services.
Home-page: https://www.botai.smartdataautomation.com/
Author: Camilo Sarmiento
Author-email: csarmiento@smartdataautomation.com
License: BSD-3-Clause
Classifier: Environment :: Web Environment
Classifier: Framework :: Django
Classifier: Framework :: Django :: 3.2
Classifier: Intended Audience :: Developers
Classifier: License :: OSI Approved :: BSD License
Classifier: Operating System :: OS Independent
Classifier: Programming Language :: Python
Classifier: Programming Language :: Python :: 3
Classifier: Programming Language :: Python :: 3 :: Only
Classifier: Programming Language :: Python :: 3.8
Classifier: Programming Language :: Python :: 3.9
Classifier: Topic :: Internet :: WWW/HTTP
Classifier: Topic :: Internet :: WWW/HTTP :: Dynamic Content
Requires-Python: >=3.7
License-File: LICENSE
Requires-Dist: Django
Requires-Dist: aiml
Requires-Dist: aioredis
Requires-Dist: boto3
Requires-Dist: botocore
Requires-Dist: django-cors-middleware
Requires-Dist: django-crontab
Requires-Dist: django-oauth-toolkit
Requires-Dist: djangorestframework
Requires-Dist: djongo
Requires-Dist: gunicorn
Requires-Dist: httplib2
Requires-Dist: httptools
Requires-Dist: oauth2client
Requires-Dist: oauthlib
Requires-Dist: requests
Requires-Dist: urllib3
Requires-Dist: uvicorn
Requires-Dist: uvloop
Requires-Dist: python-prctl
Requires-Dist: django-mysql
Requires-Dist: psycopg2-binary
Requires-Dist: django-redis
Requires-Dist: django-model-utils
Requires-Dist: jsonrpcclient
Requires-Dist: reportlab
